uidom/__init__.py
uidom/alpinejs/__init__.py
uidom/alpinejs/dataset.py
uidom/alpinejs/ripple_btn.py
uidom/cli/__init__.py
uidom/cli/_cli.py
uidom/cli/cli.py
uidom/dom/__init__.py
uidom/dom/htmldocument.py
uidom/dom/htmlelement.py
uidom/dom/icons.py
uidom/dom/jinja.py
uidom/dom/src/__init__.py
uidom/dom/src/component.py
uidom/dom/src/csstags.py
uidom/dom/src/dom1core.py
uidom/dom/src/dom_tag.py
uidom/dom/src/ext.py
uidom/dom/src/html_string.py
uidom/dom/src/htmltags.py
uidom/dom/src/jinjatags.py
uidom/dom/src/main.py
uidom/dom/src/parse_html.py
uidom/dom/src/pythontags.py
uidom/dom/src/sphinxtags.py
uidom/dom/src/svgtags.py
uidom/dom/src/utils/__init__.py
uidom/dom/src/utils/dom_util.py
uidom/dom/src/utils/sheets.py
uidom/dom/src/ws_rpc.py
uidom/dom/ui.py
uidom/dom/uniqueid.py
uidom/edge_db/__init__.py
uidom/edge_db/ql.py
uidom/elements/__init__.py
uidom/elements/booleans.py
uidom/elements/buttons.py
uidom/elements/chars.py
uidom/elements/dates.py
uidom/elements/enums.py
uidom/elements/floats.py
uidom/elements/integers.py
uidom/examples/links.py
uidom/examples/toggle.py
uidom/htmx/__init__.py
uidom/htmx/middleware.py
uidom/reloader/__init__.py
uidom/reloader/_app.py
uidom/reloader/_models.py
uidom/reloader/_notify.py
uidom/reloader/_types.py
uidom/reloader/_watch.py
uidom/reloader/script/reloader.js
uidom/response/__init__.py
uidom/response/starlette.py
uidom/routing/__init__.py
uidom/routing/fastapi.py
uidom/scripts/__init__.py
uidom/scripts/html_element.js
uidom/scripts/xcomponent.js
uidom/settings/__init__.py
uidom/settings/commands.py
uidom/settings/document.py
uidom/settings/paths.py
uidom/slots/__init__.py
uidom/slots/custom_element_slot.py
uidom/slots/slots.py
uidom/slots/web_component_slot.py
uidom/utils/__init__.py
uidom/utils/functional.py
uidom/utils/logger.py
uidom/utils/parameters.py
uidom/web_io/__init__.py
uidom/web_io/_adapter.py
uidom/web_io/_events.py
uidom/web_io/_protocol.py
uidom/web_io/_types.py
uidom-0.4a20.dist-info/entry_points.txt
uidom-0.4a20.dist-info/LICENSE
uidom-0.4a20.dist-info/METADATA
uidom-0.4a20.dist-info/WHEEL
uidom-0.4a20.dist-info/RECORD
