Metadata-Version: 2.1
Name: uidom
Version: 0.4a20
Summary: HTML library
License: MIT
Author: bitplorer
Author-email: bitplorer@outlook.com
Requires-Python: >=3.10,<4.0
Classifier: License :: OSI Approved :: MIT License
Classifier: Programming Language :: Python :: 3
Classifier: Programming Language :: Python :: 3.10
Classifier: Programming Language :: Python :: 3.11
Classifier: Programming Language :: Python :: 3.12
Provides-Extra: dev
Provides-Extra: fastapi
Provides-Extra: fastapidev
Requires-Dist: Jinja2 (>=3.0.1,<4.0.0)
Requires-Dist: anyio (>=3.6.2,<4.0.0)
Requires-Dist: fastapi (>=0.103.1) ; extra == "fastapi" or extra == "fastapidev"
Requires-Dist: marko (>=1.3.0,<2.0.0)
Requires-Dist: pytailwindcss (>=0.1.4) ; extra == "dev" or extra == "fastapidev"
Requires-Dist: typer (>=0.9.0,<0.10.0)
Requires-Dist: uvicorn[standard] (>=0.18.2,<0.19.0) ; extra == "dev" or extra == "fastapi" or extra == "fastapidev"
Requires-Dist: valio (>=0.1.0-beta.5,<0.2.0)
Requires-Dist: watchgod (>=0.8.2) ; extra == "dev" or extra == "fastapidev"
